CHANGES.md
LICENSE
README.md
python_google_speak/__init__.py
python_google_speak/cli.py
python_google_speak/speech_generator.py
python_google_speak/speech_output.py
python_google_speak/test/__init__.py
python_google_speak/test/data/hallo.mp3
python_google_speak/test/data/hello.mp3
python_google_speak/test/test_python_google_speak.py
python_google_speak-0.2.2.dist-info/LICENSE
python_google_speak-0.2.2.dist-info/METADATA
python_google_speak-0.2.2.dist-info/WHEEL
python_google_speak-0.2.2.dist-info/entry_points.txt
python_google_speak-0.2.2.dist-info/RECORD
