Metadata-Version: 2.1
Name: python-google-speak
Version: 0.2.2
Summary: Simple class to create speech files using the Google translate URL
Author: Marcus Rickert
Author-email: marcus.rickert@web.de
Requires-Python: >=3.7,<4.0
Classifier: Programming Language :: Python :: 3
Classifier: Programming Language :: Python :: 3.7
Classifier: Programming Language :: Python :: 3.8
Classifier: Programming Language :: Python :: 3.9
Classifier: Programming Language :: Python :: 3.10
Classifier: Programming Language :: Python :: 3.11
Classifier: Programming Language :: Python :: 3.12
Classifier: Programming Language :: Python :: 3.13
Requires-Dist: playsound3 (>=1.3.0)
Requires-Dist: requests (>=2.27.1)
